{"vue_nuxt.js_nuxt.js 按需引入 highlight.js 代码高亮插件.md":"a191cf8a","vue_nuxt.js_前端使用nuxt框架，配置本地https访问.md":"ca4c13d2","vue_通用_vue点击遮罩层内功能区以外的地方，遮罩层关闭.md":"7c4a6400","vue_通用_遮罩层阻止默认滚动事件.md":"471f404c","index.md":"fd6cb8f4","关于.md":"296d8253","基础知识_css_css动画资源收集.md":"29142f45","基础知识_css_css实现背景图尺寸不随浏览器缩放而变化的两种方法.md":"3912ff70","基础知识_css_出故障的文字.md":"481b39ed","基础知识_css_渐变背景动画效果.md":"48030ee5","基础知识_css_鬼影渐变效果按钮.md":"a6b50859","基础知识_javascript_判断是否空对象.md":"97f8d5a4","基础知识_vite_vite3添加别名.md":"80df4021","基础知识_npm_使用tree生成项目目录树结构.md":"a9a91394","基础知识_如何根据系统主题自动更改css暗黑模式（也可手动更改）.md":"83734a8f","基础知识_小程序_uni-app获取当前页参数.md":"94a4ecda","基础知识_小程序_uniapp分包.md":"81b946b8","基础知识_小程序_vendor.js 过大的处理方式.md":"aa7cf008","操作系统_linux_linux基础命令.md":"422f19b6","操作系统_macos_macos 安装 mongodb.md":"248a650c","杂项_前端面试_前端面试一.md":"fa061bff","杂项_收集癖_10个黑科技网站.md":"507441cd","杂项_浏览器_双内核浏览器内核切换控制技术.md":"0e69620d","杂项_疑难杂症_shadowsocks-添加pac自定义规则.md":"ebdec7b2","杂项_疑难杂症_禁止打开f12开发者工具.md":"d9783002","杂项_疑难杂症_解决 failed to connect to github.com port 443connection timed out.md":"f958ab84","编程知识_github_git提交空文件夹的技巧.md":"ff5cdcaa","编辑器_vscode_vs code为什么自动补全后引号内变成灰色，导致引号内智能感知失效？.md":"df76027a"}
